fastgraphql/__init__.py
fastgraphql/application.py
fastgraphql/ariadne.py
fastgraphql/context.py
fastgraphql/exceptions.py
fastgraphql/factory.py
fastgraphql/fastapi.py
fastgraphql/injection.py
fastgraphql/py.typed
fastgraphql/scalars.py
fastgraphql/schema.py
fastgraphql/sqlalchemy.py
fastgraphql/types.py
fastgraphql/utils.py
fastgraphql-0.0.12.dist-info/METADATA
fastgraphql-0.0.12.dist-info/LICENSE
fastgraphql-0.0.12.dist-info/WHEEL
fastgraphql-0.0.12.dist-info/RECORD
