Metadata-Version: 2.1
Name: fastgraphql
Version: 0.0.12
Summary: FastGraphQL is intended to help developer create code driven GraphQL APIs
Home-page: https://github.com/hugowschneider/fastgraphql
License: MIT
Keywords: graphql,fastgraphql
Author: Hugo Wruck Schneider
Author-email: hugowschneider@gmail.com
Requires-Python: >=3.8.1,<4.0.0
Classifier: Intended Audience :: Developers
Classifier: License :: OSI Approved :: MIT License
Classifier: Operating System :: OS Independent
Classifier: Programming Language :: Python
Classifier: Programming Language :: Python :: 3
Classifier: Programming Language :: Python :: 3.9
Classifier: Programming Language :: Python :: 3.10
Classifier: Programming Language :: Python :: 3.11
Classifier: Programming Language :: Python :: 3.10
Classifier: Programming Language :: Python :: 3.8
Classifier: Programming Language :: Python :: 3.9
Classifier: Topic :: Software Development :: Libraries :: Python Modules
Provides-Extra: all
Provides-Extra: ariadne
Provides-Extra: fastapi
Provides-Extra: sqlalchemy
Requires-Dist: SQLAlchemy[mypy] (>=1.4.0,<1.5.0) ; extra == "sqlalchemy" or extra == "all"
Requires-Dist: ariadne (>=0.14,<1.0) ; extra == "ariadne" or extra == "all"
Requires-Dist: fastapi (>=0.70,<1.0) ; extra == "fastapi" or extra == "all"
Requires-Dist: graphql-core (>=3.0,<4.0)
Requires-Dist: pydantic (>=1.10.2,<2.0.0)
Project-URL: Repository, https://github.com/hugowschneider/fastgraphql
